fyodorov_utils/__init__.py
fyodorov_utils/auth/__init__.py
fyodorov_utils/auth/auth.py
fyodorov_utils/auth/endpoints.py
fyodorov_utils/config/__init__.py
fyodorov_utils/config/config.py
fyodorov_utils/config/service_discovery.py
fyodorov_utils/config/supabase.py
fyodorov_utils/decorators/__init__.py
fyodorov_utils/decorators/logging.py
fyodorov_utils/services/__init__.py
fyodorov_utils/services/base.py
fyodorov_utils/services/tool.py
fyodorov_utils/services/yaml.py
fyodorov_utils-0.4.52.dist-info/METADATA
fyodorov_utils-0.4.52.dist-info/WHEEL
fyodorov_utils-0.4.52.dist-info/top_level.txt
fyodorov_utils-0.4.52.dist-info/RECORD
