Metadata-Version: 2.4
Name: fyodorov_utils
Version: 0.4.52
Summary: Utilities for the Fyodorov AI suite
Author-email: Daniel Ransom <02masseur.alibis@icloud.com>
Project-URL: Homepage, https://github.com/FyodorovAI/fyodorov-utils
Project-URL: Issues, https://github.com/FyodorovAI/fyodorov-utils/issues
Classifier: Programming Language :: Python :: 3
Classifier: License :: OSI Approved :: MIT License
Classifier: Operating System :: OS Independent
Requires-Python: >=3.8
Requires-Dist: fastapi
Requires-Dist: asyncio
Requires-Dist: PyJWT
Requires-Dist: starlette
Requires-Dist: supabase
Requires-Dist: gotrue>=2
Requires-Dist: pydantic>=2.11.3
Requires-Dist: fyodorov_llm_agents==0.4.98
